Workbook

Sheet Dashboard
A1: 🛒 E-COMMERCE SALES ANALYTICS DASHBOARD
X2: Category | Y2: Revenue | Z2: Profit | AB2: Region | AC2: Revenue | AD2: Profit | AF2: Payment | AG2: Revenue | AI2: Year | AJ2: Revenue | AL2: Tier | AM2: Spend | AO2: Churn | AP2: Count | AR2: Segment | AS2: Revenue | AU2: Category | AV2: Stock
X3: Home & Kitchen | Y3: 27721930 | Z3: 11790500 | AB3: East | AC3: 33225560 | AD3: 14109386 | AF3: Cash on Delivery | AG3: 18342180 | AI3: 2022 | AJ3: 6.0209059e+08 | AL3: Platinum | AM3: 78844986 | AO3: High | AP3: 486 | AR3: Consumer | AS3: 33912723 | AU3: Clothing | AV3: 4728
A4: Orders · Product_Master · Customer_Segments · Monthly_KPIs | 2,000 Orders · 70 Products · 1,001 Customers | X4: Electronics | Y4: 26271273 | Z4: 11293622 | AB4: North | AC4: 32398260 | AD4: 13803137 | AF4: Credit Card | AG4: 17606593 | AI4: 2023 | AJ4: 5.9893072e+08 | AL4: Gold | AM4: 19511511 | AO4: Low | AP4: 263 | AR4: Corporate | AS4: 32784494 | AU4: Books | AV4: 4114
X5: Sports & Fitness | Y5: 26037256 | Z5: 11003922 | AB5: South | AC5: 32090536 | AD5: 13635765 | AF5: Debit Card | AG5: 17846309 | AI5: 2024 | AJ5: 6.1960259e+08 | AL5: Silver | AM5: 5380142.1 | AO5: Medium | AP5: 252 | AR5: Home Office | AS5: 32042979 | AU5: Electronics | AV5: 3617
B6: 💰 TOTAL REVENUE | D6: 📦 TOTAL ORDERS | F6: 📈 GROSS PROFIT | H6: 🔄 RETURN RATE | J6: ⭐ AVG RATING | X6: Clothing | Y6: 25348910 | Z6: 10931519 | AB6: West | AC6: 30840014 | AD6: 13189564 | AF6: Digital Wallet | AG6: 19558235 | AL6: Bronze | AM6: 221608.9 | AR6: SMB | AS6: 29814175 | AU6: Home & Kitchen | AV6: 3295
B7: =SUM(Orders!U2:U2001) -> 1.2855437e+08 | D7: =COUNTA(Orders!A2:A2001)-1 -> 1999 | F7: =SUM(Orders!W2:W2001) -> 54737852 | H7: =COUNTIF(Orders!AC2:AC2001,"Yes")/COUNTA(Orders!A2:A2001) -> 0 | J7: =AVERAGE(Orders!AC2:AC2001) -> 2.9184211 | X7: Books | Y7: 23175002 | Z7: 9718289.5 | AF7: EMI | AG7: 19189715 | AU7: Sports & Fitness | AV7: 2813
B8: Orders sheet | D8: Order transactions | F8: Orders sheet | H8: Orders sheet | J8: Customer satisfaction | AF8: Net Banking | AG8: 18581427
AF9: UPI | AG9: 17429912
B11: 👥 UNIQUE CUSTOMERS | D11: 📦 TOTAL PRODUCTS | F11: ⚠ HIGH CHURN RISK | H11: 🏆 BESTSELLERS | J11: 📊 NEW CUSTOMERS
B12: =COUNTA(Customer_Segments!A2:A1002)-1 -> 1000 | D12: =COUNTA(Product_Master!A2:A71)-1 -> 69 | F12: =COUNTIF(Customer_Segments!N2:N1002,"High") -> 486 | H12: =COUNTIF(Product_Master!L2:L71,"Yes") -> 31 | J12: =SUM(Monthly_KPIs!M2:M721) -> 36943
B13: Customer_Segments | D13: Product_Master | F13: Customer_Segments | H13: Product_Master | J13: Monthly_KPIs
B16: ▌ SALES ANALYSIS (Sources: Orders + Monthly_KPIs)
B37: ▌ PAYMENT & TREND ANALYSIS (Sources: Orders + Monthly_KPIs)
B58: ▌ CUSTOMER & PRODUCT ANALYSIS (Sources: Customer_Segments + Product_Master)
B79: ▌ SEGMENT & STOCK SNAPSHOT (Sources: Orders + Product_Master)

Sheet KPI_Calculations
A1: 📈 KPI CALCULATIONS — Formulas Referencing All 4 Raw Data Sheets
A3: KPI Name | B3: Excel Formula | C3: Calculated Value | D3: Source Sheet
A4: ORDERS KPIs — Source: Orders sheet
A5: Total Orders | B5: =COUNTA(Orders!A2:A2001)-1 -> 1999 | C5: =COUNTA(Orders!A2:A2001)-1 -> 1999 | D5: Orders
A6: Total Revenue (INR) | B6: =SUM(Orders!U2:U2001) -> 1.2855437e+08 | C6: =SUM(Orders!U2:U2001) -> 1.2855437e+08 | D6: Orders
A7: Total Gross Profit (INR) | B7: =SUM(Orders!W2:W2001) -> 54737852 | C7: =SUM(Orders!W2:W2001) -> 54737852 | D7: Orders
A8: Avg Order Value (INR) | B8: =AVERAGE(Orders!U2:U2001) -> 64277.185 | C8: =AVERAGE(Orders!U2:U2001) -> 64277.185 | D8: Orders
A9: Avg Profit Margin % | B9: =AVERAGE(Orders!X2:X2001)/100 -> 0.42552375 | C9: =AVERAGE(Orders!X2:X2001)/100 -> 0.42552375 | D9: Orders
A10: Avg Delivery Days | B10: =AVERAGE(Orders!I2:I2001) -> 5.004 | C10: =AVERAGE(Orders!I2:I2001) -> 5.004 | D10: Orders
A11: Total Shipping Cost (INR) | B11: =SUM(Orders!Y2:Y2001) -> 175778 | C11: =SUM(Orders!Y2:Y2001) -> 175778 | D11: Orders
A12: Return Count | B12: =COUNTIF(Orders!AC2:AC2001,"Yes") -> 0 | C12: =COUNTIF(Orders!AC2:AC2001,"Yes") -> 0 | D12: Orders
A13: Return Rate % | B13: =COUNTIF(Orders!AC2:AC2001,"Yes")/COUNTA(Orders!A2:A2001) -> 0 | C13: =COUNTIF(Orders!AC2:AC2001,"Yes")/COUNTA(Orders!A2:A2001) -> 0 | D13: Orders
A14: Avg Customer Rating | B14: =AVERAGE(Orders!AC2:AC2001) -> 2.9184211 | C14: =AVERAGE(Orders!AC2:AC2001) -> 2.9184211 | D14: Orders
A15: PRODUCT KPIs — Source: Product_Master sheet
A16: Total Products in Catalogue | B16: =COUNTA(Product_Master!A2:A71)-1 -> 69 | C16: =COUNTA(Product_Master!A2:A71)-1 -> 69 | D16: Product_Master
A17: Total Stock Units | B17: =SUM(Product_Master!H2:H71) -> 18567 | C17: =SUM(Product_Master!H2:H71) -> 18567 | D17: Product_Master
A18: Avg Product Rating | B18: =AVERAGE(Product_Master!I2:I71) -> 4.1528571 | C18: =AVERAGE(Product_Master!I2:I71) -> 4.1528571 | D18: Product_Master
A19: Avg MRP (INR) | B19: =AVERAGE(Product_Master!F2:F71) -> 24564.374 | C19: =AVERAGE(Product_Master!F2:F71) -> 24564.374 | D19: Product_Master
A20: Avg Cost Price (INR) | B20: =AVERAGE(Product_Master!G2:G71) -> 12876.48 | C20: =AVERAGE(Product_Master!G2:G71) -> 12876.48 | D20: Product_Master
A21: Bestseller Count | B21: =COUNTIF(Product_Master!L2:L71,"Yes") -> 31 | C21: =COUNTIF(Product_Master!L2:L71,"Yes") -> 31 | D21: Product_Master
A22: CUSTOMER KPIs — Source: Customer_Segments sheet
A23: Total Unique Customers | B23: =COUNTA(Customer_Segments!A2:A1002)-1 -> 1000 | C23: =COUNTA(Customer_Segments!A2:A1002)-1 -> 1000 | D23: Customer_Segments
A24: Total Customer Spend (INR) | B24: =SUM(Customer_Segments!G2:G1002) -> 1.0395825e+08 | C24: =SUM(Customer_Segments!G2:G1002) -> 1.0395825e+08 | D24: Customer_Segments
A25: Avg Customer Order Value (INR) | B25: =AVERAGE(Customer_Segments!H2:H1002) -> 14083.683 | C25: =AVERAGE(Customer_Segments!H2:H1002) -> 14083.683 | D25: Customer_Segments
A26: Platinum Tier Customers | B26: =COUNTIF(Customer_Segments!M2:M1002,"Platinum") -> 525 | C26: =COUNTIF(Customer_Segments!M2:M1002,"Platinum") -> 525 | D26: Customer_Segments
A27: High Churn Risk Customers | B27: =COUNTIF(Customer_Segments!N2:N1002,"High") -> 486 | C27: =COUNTIF(Customer_Segments!N2:N1002,"High") -> 486 | D27: Customer_Segments
A28: MONTHLY TREND KPIs — Source: Monthly_KPIs sheet
A29: Total Revenue (Monthly KPIs) | B29: =SUM(Monthly_KPIs!F2:F721) -> 1.8206239e+09 | C29: =SUM(Monthly_KPIs!F2:F721) -> 1.8206239e+09 | D29: Monthly_KPIs
A30: Total Gross Profit (Monthly KPIs) | B30: =SUM(Monthly_KPIs!H2:H721) -> 7.2571967e+08 | C30: =SUM(Monthly_KPIs!H2:H721) -> 7.2571967e+08 | D30: Monthly_KPIs
A31: Total New Customers (All Months) | B31: =SUM(Monthly_KPIs!M2:M721) -> 36943 | C31: =SUM(Monthly_KPIs!M2:M721) -> 36943 | D31: Monthly_KPIs
A32: Total Returns (All Months) | B32: =SUM(Monthly_KPIs!L2:L721) -> 10100.84 | C32: =SUM(Monthly_KPIs!L2:L721) -> 10100.84 | D32: Monthly_KPIs
A33: Avg Monthly Return Rate % | B33: =AVERAGE(Monthly_KPIs!K2:K721)/100 -> 0.14554167 | C33: =AVERAGE(Monthly_KPIs!K2:K721)/100 -> 0.14554167 | D33: Monthly_KPIs

Sheet Pivot_Tables
A1: 📊 PIVOT ANALYSIS — Orders | Product_Master | Customer_Segments | Monthly_KPIs
A3: ▌ FROM: Orders
A5: Revenue & Profit by Category | H5: Revenue & Profit by Region
A6: Category | B6: Sales_Amount_INR | C6: Gross_Profit_INR | D6: Quantity | H6: Region | I6: Sales_Amount_INR | J6: Gross_Profit_INR
A7: Books | B7: 23175002 | C7: 9718289.5 | D7: 1128 | H7: East | I7: 33225560 | J7: 14109386
A8: Clothing | B8: 25348910 | C8: 10931519 | D8: 1192 | H8: North | I8: 32398260 | J8: 13803137
A9: Electronics | B9: 26271273 | C9: 11293622 | D9: 1203 | H9: South | I9: 32090536 | J9: 13635765
A10: Home & Kitchen | B10: 27721930 | C10: 11790500 | D10: 1312 | H10: West | I10: 30840014 | J10: 13189564
A11: Sports & Fitness | B11: 26037256 | C11: 11003922 | D11: 1152 | H11: TOTAL | I11: =SUM(I7:I10) -> 1.2855437e+08 | J11: =SUM(J7:J10) -> 54737852
A12: TOTAL | B12: =SUM(B7:B11) -> 1.2855437e+08 | C12: =SUM(C7:C11) -> 54737852 | D12: =SUM(D7:D11) -> 5987
H13: Revenue by Payment Method
A14: Orders by Customer Segment | H14: Payment_Method | I14: Sales_Amount_INR | J14: Gross_Profit_INR
A15: Customer_Segment | B15: Sales_Amount_INR | C15: Quantity | H15: Cash on Delivery | I15: 18342180 | J15: 7761344.8
A16: Consumer | B16: 33912723 | C16: 1599 | H16: Credit Card | I16: 17606593 | J16: 7495480.2
A17: Corporate | B17: 32784494 | C17: 1485 | H17: Debit Card | I17: 17846309 | J17: 7563946.9
A18: Home Office | B18: 32042979 | C18: 1496 | H18: Digital Wallet | I18: 19558235 | J18: 8453126.3
A19: SMB | B19: 29814175 | C19: 1407 | H19: EMI | I19: 19189715 | J19: 8134982.8
A20: TOTAL | B20: =SUM(B16:B19) -> 1.2855437e+08 | C20: =SUM(C16:C19) -> 5987 | H20: Net Banking | I20: 18581427 | J20: 7820222.2
H21: UPI | I21: 17429912 | J21: 7508748.5
A22: Order Status Breakdown | H22: TOTAL | I22: 1.2855437e+08 | J22: =SUM(J15:J21) -> 54737852
A23: Order_Status | B23: Sales_Amount_INR | C23: Quantity
A24: Cancelled | B24: 12933513 | C24: 592 | H24: Returns Analysis by Category
A25: Delivered | B25: 88486514 | C25: 4145 | H25: Category | I25: Sales_Amount_INR
A26: Processing | B26: 7109221.5 | C26: 334 | H26: Books | I26: 2188264.4
A27: Returned | B27: 8007318.5 | C27: 349 | H27: Clothing | I27: 3154750.5
A28: Shipped | B28: 12017804 | C28: 567 | H28: Electronics | I28: 2516087.8
A29: TOTAL | B29: =SUM(B24:B28) -> 1.2855437e+08 | C29: =SUM(C24:C28) -> 5987 | H29: Home & Kitchen | I29: 3003355.4
H30: Sports & Fitness | I30: 3000840.7
H31: TOTAL | I31: =SUM(I26:I30) -> 13863299
A34: ▌ FROM: Product_Master
A36: Stock & Avg Rating by Category | H36: MRP vs Cost Price by Category
A37: Category | B37: Stock_Units | C37: Avg_Rating | D37: Total_Reviews | H37: Category | I37: MRP_INR | J37: Cost_Price_INR
A38: Books | B38: 274.26667 | C38: 4.36 | D38: 2221.8667 | H38: Books | I38: 22997.669 | J38: 11764.972
A39: Clothing | B39: 315.2 | C39: 4.08 | D39: 2665.4667 | H39: Clothing | I39: 23575.7 | J39: 12291.951
A40: Electronics | B40: 241.13333 | C40: 4.1266667 | D40: 2428.7333 | H40: Electronics | I40: 24934.471 | J40: 13235.553
A41: Home & Kitchen | B41: 219.66667 | C41: 4.1066667 | D41: 2215.0667 | H41: Home & Kitchen | I41: 25207.675 | J41: 13602.933
A42: Sports & Fitness | B42: 281.3 | C42: 4.06 | D42: 2327.7 | H42: Sports & Fitness | I42: 26877.348 | J42: 13792.245
A43: TOTAL | B43: =SUM(B38:B42) -> 1331.5667 | C43: =SUM(C38:C42) -> 20.733333 | D43: =SUM(D38:D42) -> 11858.833 | H43: TOTAL | I43: =SUM(I38:I42) -> 123592.86 | J43: =SUM(J38:J42) -> 64687.654
A46: ▌ FROM: Customer_Segments
A48: Total Spend & Orders by Segment | H48: Churn Risk Distribution by Tier
A49: Segment | B49: Total_Spend_INR | C49: Total_Orders | D49: Avg_Order_Value | H49: Customer_Tier | I49: Total_Spend_INR | J49: Total_Orders
A50: Consumer | B50: 28796103 | C50: 4224 | D50: 3568714.9 | H50: Bronze | I50: 221608.9 | J50: 604
A51: Corporate | B51: 26715560 | C51: 3762 | D51: 4130042.6 | H51: Gold | I51: 19511511 | J51: 4142
A52: Home Office | B52: 22119632 | C52: 3417 | D52: 3042854.1 | H52: Platinum | I52: 78844986 | J52: 8032
A53: SMB | B53: 26326954 | C53: 4083 | D53: 3356154.6 | H53: Silver | I53: 5380142.1 | J53: 2708
A54: TOTAL | B54: =SUM(B50:B53) -> 1.0395825e+08 | C54: =SUM(C50:C53) -> 15486 | D54: =SUM(D50:D53) -> 14097766 | H54: TOTAL | I54: =SUM(I50:I53) -> 1.0395825e+08 | J54: =SUM(J50:J53) -> 15486
A56: Customers by Churn Risk
A57: Churn_Risk | B57: Total_Spend_INR | C57: Total_Orders
A58: High | B58: 51021329 | C58: 7254
A59: Low | B59: 26397750 | C59: 4284
A60: Medium | B60: 26539170 | C60: 3948
A61: TOTAL | B61: =SUM(B58:B60) -> 1.0395825e+08 | C61: =SUM(C58:C60) -> 15486
A63: ▌ FROM: Monthly_KPIs
A65: Annual Revenue & Profit by Year | H65: Revenue & Returns by Category
A66: Year | B66: Revenue_INR | C66: Gross_Profit_INR | D66: Total_Orders | H66: Category | I66: Revenue_INR | J66: Returns | K66: New_Customers
A67: 2022 | B67: 6.0209059e+08 | C67: 2.3919742e+08 | D67: 37601 | H67: Books | I67: 3.647317e+08 | J67: 2268 | K67: 7390
A68: 2023 | B68: 5.9893072e+08 | C68: 2.3831658e+08 | D68: 38201 | H68: Clothing | I68: 3.7837895e+08 | J68: 1981 | K68: 7092
A69: 2024 | B69: 6.1960259e+08 | C69: 2.4820567e+08 | D69: 38828 | H69: Electronics | I69: 3.4150983e+08 | J69: 2148 | K69: 7240
A70: TOTAL | B70: =SUM(B67:B69) -> 1.8206239e+09 | C70: =SUM(C67:C69) -> 7.2571967e+08 | D70: =SUM(D67:D69) -> 114630 | H70: Home & Kitchen | I70: 3.7201309e+08 | J70: 1975 | K70: 8119
H71: Sports & Fitness | I71: 3.6399034e+08 | J71: 2107 | K71: 7102
A72: Performance by Region (Monthly KPIs) | H72: TOTAL | I72: =SUM(I67:I71) -> 1.8206239e+09 | J72: =SUM(J67:J71) -> 10479 | K72: =SUM(K67:K71) -> 36943
A73: Region | B73: Revenue_INR | C73: Gross_Profit_INR | D73: New_Customers
A74: East | B74: 4.6413067e+08 | C74: 1.8543723e+08 | D74: 8941
A75: North | B75: 4.6238808e+08 | C75: 1.8396683e+08 | D75: 9400
A76: South | B76: 4.4060331e+08 | C76: 1.7517984e+08 | D76: 8957
A77: West | B77: 4.5350184e+08 | C77: 1.8113577e+08 | D77: 9645
A78: TOTAL | B78: =SUM(B74:B77) -> 1.8206239e+09 | C78: =SUM(C74:C77) -> 7.2571967e+08 | D78: =SUM(D74:D77) -> 36943

Sheet Data_Cleaning
A1: 🔍 DATA QUALITY REPORT — E-Commerce Sales (All 4 Tables)
A3: Orders (2000 rows × 29 cols) | G3: Product_Master (70 rows × 12 cols) | M3: Customer_Segments (1001 rows × 14 cols) | S3: Monthly_KPIs (720 rows × 13 cols)
A4: Column | B4: Non-Null | C4: Missing | D4: Miss % | E4: Data Type | G4: Column | H4: Non-Null | I4: Missing | J4: Miss % | K4: Data Type | M4: Column | N4: Non-Null | O4: Missing | P4: Miss % | Q4: Data Type | S4: Column | T4: Non-Null | U4: Missing | V4: Miss % | W4: Data Type
A5: Order_ID | B5: 2000 | C5: 0 | D5: 0 | E5: str | G5: Product_ID | H5: 70 | I5: 0 | J5: 0 | K5: str | M5: Customer_ID | N5: 1001 | O5: 0 | P5: 0 | Q5: str | S5: Year | T5: 720 | U5: 0 | V5: 0 | W5: int64
A6: Customer_ID | B6: 2000 | C6: 0 | D6: 0 | E6: str | G6: Product_Name | H6: 70 | I6: 0 | J6: 0 | K6: str | M6: Customer_Name | N6: 1001 | O6: 0 | P6: 0 | Q6: str | S6: Month | T6: 720 | U6: 0 | V6: 0 | W6: str
A7: Customer_Name | B7: 2000 | C7: 0 | D7: 0 | E7: str | G7: Category | H7: 70 | I7: 0 | J7: 0 | K7: str | M7: Segment | N7: 1001 | O7: 0 | P7: 0 | Q7: str | S7: Category | T7: 720 | U7: 0 | V7: 0 | W7: str
A8: Customer_Email | B8: 2000 | C8: 0 | D8: 0 | E8: str | G8: Sub_Category | H8: 70 | I8: 0 | J8: 0 | K8: str | M8: State | N8: 1001 | O8: 0 | P8: 0 | Q8: str | S8: Region | T8: 720 | U8: 0 | V8: 0 | W8: str
A9: Customer_Segment | B9: 2000 | C9: 0 | D9: 0 | E9: str | G9: Brand | H9: 70 | I9: 0 | J9: 0 | K9: str | M9: Region | N9: 1001 | O9: 0 | P9: 0 | Q9: str | S9: Total_Orders | T9: 720 | U9: 0 | V9: 0 | W9: int64
A10: Order_Date | B10: 2000 | C10: 0 | D10: 0 | E10: str | G10: MRP_INR | H10: 70 | I10: 0 | J10: 0 | K10: float64 | M10: Total_Orders | N10: 1001 | O10: 0 | P10: 0 | Q10: int64 | S10: Revenue_INR | T10: 720 | U10: 0 | V10: 0 | W10: float64
A11: Ship_Date | B11: 2000 | C11: 0 | D11: 0 | E11: str | G11: Cost_Price_INR | H11: 70 | I11: 0 | J11: 0 | K11: float64 | M11: Total_Spend_INR | N11: 1001 | O11: 0 | P11: 0 | Q11: float64 | S11: COGS_INR | T11: 720 | U11: 0 | V11: 0 | W11: float64
A12: Delivery_Date | B12: 2000 | C12: 0 | D12: 0 | E12: str | G12: Stock_Units | H12: 70 | I12: 0 | J12: 0 | K12: int64 | M12: Avg_Order_Value | N12: 1001 | O12: 0 | P12: 0 | Q12: float64 | S12: Gross_Profit_INR | T12: 720 | U12: 0 | V12: 0 | W12: float64
A13: Days_to_Deliver | B13: 2000 | C13: 0 | D13: 0 | E13: int64 | G13: Avg_Rating | H13: 70 | I13: 0 | J13: 0 | K13: float64 | M13: Last_Order_Date | N13: 1001 | O13: 0 | P13: 0 | Q13: str | S13: Profit_Margin_Pct | T13: 720 | U13: 0 | V13: 0 | W13: float64
A14: Region | B14: 2000 | C14: 0 | D14: 0 | E14: str | G14: Total_Reviews | H14: 70 | I14: 0 | J14: 0 | K14: int64 | M14: Days_Since_Last_Order | N14: 1001 | O14: 0 | P14: 0 | Q14: int64 | S14: Avg_Order_Value | T14: 720 | U14: 0 | V14: 0 | W14: float64
A15: State | B15: 2000 | C15: 0 | D15: 0 | E15: str | G15: Launch_Date | H15: 70 | I15: 0 | J15: 0 | K15: str | M15: Preferred_Category | N15: 1001 | O15: 0 | P15: 0 | Q15: str | S15: Returns | T15: 720 | U15: 0 | V15: 0 | W15: int64
A16: City | B16: 2000 | C16: 0 | D16: 0 | E16: str | G16: Bestseller | H16: 70 | I16: 0 | J16: 0 | K16: str | M16: Preferred_Payment | N16: 1001 | O16: 0 | P16: 0 | Q16: str | S16: Return_Rate_Pct | T16: 720 | U16: 0 | V16: 0 | W16: float64
A17: Product_ID | B17: 2000 | C17: 0 | D17: 0 | E17: str | M17: Customer_Tier | N17: 1001 | O17: 0 | P17: 0 | Q17: str | S17: New_Customers | T17: 720 | U17: 0 | V17: 0 | W17: int64
A18: Product_Name | B18: 2000 | C18: 0 | D18: 0 | E18: str | M18: Churn_Risk | N18: 1001 | O18: 0 | P18: 0 | Q18: str
A19: Category | B19: 2000 | C19: 0 | D19: 0 | E19: str
A20: Sub_Category | B20: 2000 | C20: 0 | D20: 0 | E20: str
A21: Brand | B21: 2000 | C21: 0 | D21: 0 | E21: str
A22: Quantity | B22: 2000 | C22: 0 | D22: 0 | E22: int64
A23: Unit_Price_INR | B23: 2000 | C23: 0 | D23: 0 | E23: float64
A24: Discount_Pct | B24: 2000 | C24: 0 | D24: 0 | E24: int64
A25: Sales_Amount_INR | B25: 2000 | C25: 0 | D25: 0 | E25: float64
A26: COGS_INR | B26: 2000 | C26: 0 | D26: 0 | E26: float64
A27: Gross_Profit_INR | B27: 2000 | C27: 0 | D27: 0 | E27: float64
A28: Profit_Margin_Pct | B28: 2000 | C28: 0 | D28: 0 | E28: float64
A29: Shipping_Cost_INR | B29: 2000 | C29: 0 | D29: 0 | E29: int64
A30: Payment_Method | B30: 2000 | C30: 0 | D30: 0 | E30: str
... A33: Customer_Rating | B33: 1140 | C33: 860 | D33: 0.43 | E33: float64

Sheet Orders
A1: Order_ID | B1: Customer_ID | C1: Customer_Name | D1: Customer_Email | E1: Customer_Segment | F1: Order_Date | G1: Ship_Date | H1: Delivery_Date | I1: Days_to_Deliver | J1: Region | K1: State | L1: City | M1: Product_ID | N1: Product_Name | O1: Category | P1: Sub_Category | Q1: Brand | R1: Quantity | S1: Unit_Price_INR | T1: Discount_Pct | U1: Sales_Amount_INR | V1: COGS_INR | W1: Gross_Profit_INR | X1: Profit_Margin_Pct | Y1: Shipping_Cost_INR | Z1: Payment_Method | AA1: Order_Status | AB1: Return_Flag | AC1: Customer_Rating
A2: ORD000001 | B2: CUST8557 | C2: Karan Iyer | D2: karan862@email.com | E2: SMB | F2: 2022-07-11 | G2: 2022-07-14 | H2: 2022-07-16 | I2: 2 | J2: East | K2: Odisha | L2: Odisha | M2: PRD2097 | N2: Curtain Set | O2: Home & Kitchen | P2: Decor | Q2: Amazon Basics | R2: 4 | S2: 24506.53 | T2: 10 | U2: 88223.51 | V2: 55785.82 | W2: 32437.69 | X2: 36.77 | Y2: 99 | Z2: EMI | AA2: Delivered | AB2: No | AC2: 2
A3: ORD000002 | B3: CUST5884 | C3: Meena Reddy | D3: meena262@email.com | E3: Corporate | F3: 2022-08-08 | G3: 2022-08-11 | H3: 2022-08-16 | I3: 5 | J3: West | K3: Maharashtra | L3: Mumbai | M3: PRD3376 | N3: Fantasy Epic | O3: Books | P3: Fiction | Q3: Prestige | R3: 5 | S3: 10270.25 | T3: 15 | U3: 43648.56 | V3: 26954.94 | W3: 16693.62 | X3: 38.25 | Y3: 29 | Z3: Digital Wallet | AA3: Delivered | AB3: No | AC3: 3
A4: ORD000003 | B4: CUST2265 | C4: Suresh Kumar | D4: suresh399@email.com | E4: Home Office | F4: 2022-05-07 | G4: 2022-05-10 | H4: 2022-05-15 | I4: 5 | J4: North | K4: Rajasthan | L4: Jodhpur | M4: PRD1231 | N4: USB Cable | O4: Electronics | P4: Accessories | Q4: Wiley | R4: 3 | S4: 19692.77 | T4: 15 | U4: 50216.56 | V4: 25330.64 | W4: 24885.92 | X4: 49.56 | Y4: 0 | Z4: Net Banking | AA4: Delivered | AB4: No | AC4: 2
A5: ORD000004 | B5: CUST7809 | C5: Karan Iyer | D5: karan374@email.com | E5: Corporate | F5: 2024-09-02 | G5: 2024-09-05 | H5: 2024-09-12 | I5: 7 | J5: West | K5: Maharashtra | L5: Pune | M5: PRD2977 | N5: Cricket Bat | O5: Sports & Fitness | P5: Equipment | Q5: Realme | R5: 3 | S5: 38269.13 | T5: 30 | U5: 80365.17 | V5: 40090.39 | W5: 40274.78 | X5: 50.11 | Y5: 199 | Z5: EMI | AA5: Returned | AB5: Yes
A6: ORD000005 | B6: CUST7294 | C6: Nisha Iyer | D6: nisha624@email.com | E6: Consumer | F6: 2022-03-17 | G6: 2022-03-19 | H6: 2022-03-21 | I6: 2 | J6: South | K6: Andhra Pradesh | L6: Andhra Pradesh | M6: PRD2333 | N6: Pre-Workout | O6: Sports & Fitness | P6: Nutrition | Q6: Adidas | R6: 4 | S6: 34863.8 | T6: 10 | U6: 125509.68 | V6: 67792.24 | W6: 57717.44 | X6: 45.99 | Y6: 149 | Z6: Debit Card | AA6: Returned | AB6: Yes
A7: ORD000006 | B7: CUST3565 | C7: Deepak Nair | D7: deepak66@email.com | E7: Corporate | F7: 2022-09-21 | G7: 2022-09-23 | H7: 2022-09-29 | I7: 6 | J7: South | K7: Kerala | L7: Kochi | M7: PRD2779 | N7: Power Bank | O7: Electronics | P7: Accessories | Q7: Prestige | R7: 2 | S7: 10883.7 | T7: 25 | U7: 16325.55 | V7: 10715.17 | W7: 5610.38 | X7: 34.37 | Y7: 29 | Z7: Digital Wallet | AA7: Delivered | AB7: No
A8: ORD000007 | B8: CUST6973 | C8: Vikram Gupta | D8: vikram345@email.com | E8: Corporate | F8: 2024-02-06 | G8: 2024-02-07 | H8: 2024-02-14 | I8: 7 | J8: East | K8: West Bengal | L8: Howrah | M8: PRD1635 | N8: Self-Help Guide | O8: Books | P8: Non-Fiction | Q8: Amazon Basics | R8: 2 | S8: 37105.39 | T8: 0 | U8: 74210.78 | V8: 43159.15 | W8: 31051.63 | X8: 41.84 | Y8: 29 | Z8: Credit Card | AA8: Delivered | AB8: No | AC8: 3
A9: ORD000008 | B9: CUST4859 | C9: Divya Verma | D9: divya366@email.com | E9: Corporate | F9: 2022-11-06 | G9: 2022-11-07 | H9: 2022-11-13 | I9: 6 | J9: East | K9: Bihar | L9: Bihar | M9: PRD3224 | N9: Multivitamin | O9: Sports & Fitness | P9: Nutrition | Q9: Adidas | R9: 1 | S9: 43487.84 | T9: 15 | U9: 36964.66 | V9: 18435.75 | W9: 18528.91 | X9: 50.13 | Y9: 199 | Z9: Digital Wallet | AA9: Shipped | AB9: No
A10: ORD000009 | B10: CUST6897 | C10: Deepak Nair | D10: deepak329@email.com | E10: Consumer | F10: 2024-04-20 | G10: 2024-04-23 | H10: 2024-04-30 | I10: 7 | J10: West | K10: Chhattisgarh | L10: Chhattisgarh | M10: PRD2863 | N10: HP Pavilion | O10: Electronics | P10: Laptops | Q10: Dell | R10: 5 | S10: 32463.47 | T10: 10 | U10: 146085.62 | V10: 83430.39 | W10: 62655.23 | X10: 42.89 | Y10: 29 | Z10: EMI | AA10: Delivered | AB10: No | AC10: 2
A11: ORD000010 | B11: CUST6544 | C11: Anita Kumar | D11: anita556@email.com | E11: Consumer | F11: 2024-09-10 | G11: 2024-09-12 | H11: 2024-09-17 | I11: 5 | J11: South | K11: Andhra Pradesh | L11: Andhra Pradesh | M11: PRD3664 | N11: iPhone 15 | O11: Electronics | P11: Smartphones | Q11: Puma | R11: 3 | S11: 36312.42 | T11: 0 | U11: 108937.26 | V11: 63356.15 | W11: 45581.11 | X11: 41.84 | Y11: 0 | Z11: UPI | AA11: Shipped | AB11: No
A12: ORD000011 | B12: CUST9979 | C12: Aditya Gupta | D12: aditya978@email.com | E12: SMB | F12: 2024-10-04 | G12: 2024-10-06 | H12: 2024-10-10 | I12: 4 | J12: East | K12: Assam | L12: Assam | M12: PRD2543 | N12: Xiaomi 13T | O12: Electronics | P12: Smartphones | Q12: MuscleBlaze | R12: 5 | S12: 44488.12 | T12: 30 | U12: 155708.42 | V12: 86436.36 | W12: 69272.06 | X12: 44.49 | Y12: 149 | Z12: Credit Card | AA12: Delivered | AB12: No | AC12: 4
A13: ORD000012 | B13: CUST3559 | C13: Nisha Patel | D13: nisha813@email.com | E13: SMB | F13: 2024-04-16 | G13: 2024-04-17 | H13: 2024-04-20 | I13: 3 | J13: West | K13: Goa | L13: Goa | M13: PRD4767 | N13: Air Fryer | O13: Home & Kitchen | P13: Appliances | Q13: Realme | R13: 3 | S13: 40871.07 | T13: 15 | U13: 104221.23 | V13: 54103.9 | W13: 50117.33 | X13: 48.09 | Y13: 149 | Z13: Credit Card | AA13: Returned | AB13: Yes
A14: ORD000013 | B14: CUST1142 | C14: Suresh Iyer | D14: suresh328@email.com | E14: Consumer | F14: 2023-05-17 | G14: 2023-05-19 | H14: 2023-05-23 | I14: 4 | J14: North | K14: Rajasthan | L14: Jaipur | M14: PRD2034 | N14: Air Fryer | O14: Home & Kitchen | P14: Appliances | Q14: Realme | R14: 4 | S14: 14543.99 | T14: 20 | U14: 46540.77 | V14: 31252.92 | W14: 15287.85 | X14: 32.85 | Y14: 99 | Z14: Net Banking | AA14: Delivered | AB14: No | AC14: 2
A15: ORD000014 | B15: CUST1263 | C15: Kavya Nair | D15: kavya586@email.com | E15: Home Office | F15: 2024-09-23 | G15: 2024-09-25 | H15: 2024-09-28 | I15: 3 | J15: South | K15: Kerala | L15: Kochi | M15: PRD3378 | N15: Multivitamin | O15: Sports & Fitness | P15: Nutrition | Q15: Nike | R15: 2 | S15: 29778.86 | T15: 10 | U15: 53601.95 | V15: 28883.45 | W15: 24718.5 | X15: 46.11 | Y15: 149 | Z15: UPI | AA15: Returned | AB15: Yes
A16: ORD000015 | B16: CUST6934 | C16: Divya Reddy | D16: divya464@email.com | E16: Consumer | F16: 2024-12-15 | G16: 2024-12-17 | H16: 2024-12-23 | I16: 6 | J16: North | K16: Punjab | L16: Punjab | M16: PRD2002 | N16: CAT Guide | O16: Books | P16: Education | Q16: Nike | R16: 4 | S16: 18273.69 | T16: 20 | U16: 58475.81 | V16: 32764.29 | W16: 25711.52 | X16: 43.97 | Y16: 149 | Z16: UPI | AA16: Delivered | AB16: No | AC16: 5
A17: ORD000016 | B17: CUST3320 | C17: Meena Patel | D17: meena228@email.com | E17: Home Office | F17: 2024-09-07 | G17: 2024-09-09 | H17: 2024-09-14 | I17: 5 | J17: East | K17: Bihar | L17: Bihar | M17: PRD3110 | N17: Whey Protein 1kg | O17: Sports & Fitness | P17: Nutrition | Q17: MuscleBlaze | R17: 4 | S17: 12195.76 | T17: 20 | U17: 39026.43 | V17: 20685.3 | W17: 18341.13 | X17: 47 | Y17: 49 | Z17: Net Banking | AA17: Delivered | AB17: No
A18: ORD000017 | B18: CUST4070 | C18: Karan Patel | D18: karan834@email.com | E18: Consumer | F18: 2024-02-04 | G18: 2024-02-06 | H18: 2024-02-12 | I18: 6 | J18: West | K18: Goa | L18: Goa | M18: PRD3618 | N18: TWS Earbuds | O18: Electronics | P18: Accessories | Q18: MuscleBlaze | R18: 5 | S18: 37809.9 | T18: 30 | U18: 132334.65 | V18: 76725.97 | W18: 55608.68 | X18: 42.02 | Y18: 49 | Z18: Digital Wallet | AA18: Cancelled | AB18: No
A19: ORD000018 | B19: CUST5962 | C19: Nisha Verma | D19: nisha948@email.com | E19: Corporate | F19: 2024-01-17 | G19: 2024-01-19 | H19: 2024-01-21 | I19: 2 | J19: North | K19: Delhi | L19: Noida | M19: PRD2189 | N19: Badminton Racket | O19: Sports & Fitness | P19: Equipment | Q19: HP | R19: 3 | S19: 36984.97 | T19: 15 | U19: 94311.67 | V19: 47865.88 | W19: 46445.79 | X19: 49.25 | Y19: 49 | Z19: Net Banking | AA19: Delivered | AB19: No | AC19: 2
A20: ORD000019 | B20: CUST6140 | C20: Anita Iyer | D20: anita956@email.com | E20: Consumer | F20: 2023-11-20 | G20: 2023-11-21 | H20: 2023-11-24 | I20: 3 | J20: South | K20: Kerala | L20: Kochi | M20: PRD3336 | N20: Track Pants | O20: Clothing | P20: Men | Q20: Realme | R20: 2 | S20: 46889.94 | T20: 0 | U20: 93779.88 | V20: 60365.56 | W20: 33414.32 | X20: 35.63 | Y20: 99 | Z20: Net Banking | AA20: Delivered | AB20: No | AC20: 3
A21: ORD000020 | B21: CUST8619 | C21: Amit Gupta | D21: amit873@email.com | E21: SMB | F21: 2023-10-29 | G21: 2023-11-01 | H21: 2023-11-06 | I21: 5 | J21: South | K21: Andhra Pradesh | L21: Andhra Pradesh | M21: PRD2013 | N21: Fast Charger | O21: Electronics | P21: Accessories | Q21: MuscleBlaze | R21: 1 | S21: 26291.1 | T21: 20 | U21: 21032.88 | V21: 12034.99 | W21: 8997.89 | X21: 42.78 | Y21: 199 | Z21: UPI | AA21: Delivered | AB21: No | AC21: 1
A22: ORD000021 | B22: CUST5789 | C22: Arjun Kumar | D22: arjun285@email.com | E22: Home Office | F22: 2024-10-18 | G22: 2024-10-21 | H22: 2024-10-29 | I22: 8 | J22: West | K22: Madhya Pradesh | L22: Madhya Pradesh | M22: PRD3710 | N22: Yoga Mat | O22: Sports & Fitness | P22: Equipment | Q22: Wiley | R22: 4 | S22: 20625.15 | T22: 20 | U22: 66000.48 | V22: 37942.33 | W22: 28058.15 | X22: 42.51 | Y22: 149 | Z22: UPI | AA22: Delivered | AB22: No | AC22: 5
A23: ORD000022 | B23: CUST9467 | C23: Anita Patel | D23: anita163@email.com | E23: Home Office | F23: 2023-04-19 | G23: 2023-04-22 | H23: 2023-04-25 | I23: 3 | J23: West | K23: Gujarat | L23: Vadodara | M23: PRD2186 | N23: Literary Fiction | O23: Books | P23: Fiction | Q23: MuscleBlaze | R23: 1 | S23: 34329.12 | T23: 0 | U23: 34329.12 | V23: 23421.73 | W23: 10907.39 | X23: 31.77 | Y23: 149 | Z23: Net Banking | AA23: Delivered | AB23: No | AC23: 3
A24: ORD000023 | B24: CUST6172 | C24: Meena Patel | D24: meena567@email.com | E24: Consumer | F24: 2023-10-17 | G24: 2023-10-18 | H24: 2023-10-24 | I24: 6 | J24: South | K24: Karnataka | L24: Mysuru | M24: PRD3935 | N24: Whey Protein 1kg | O24: Sports & Fitness | P24: Nutrition | Q24: Amazon Basics | R24: 3 | S24: 21296.48 | T24: 0 | U24: 63889.44 | V24: 29831.38 | W24: 34058.06 | X24: 53.31 | Y24: 99 | Z24: Cash on Delivery | AA24: Delivered | AB24: No | AC24: 2
A25: ORD000024 | B25: CUST8166 | C25: Pooja Patel | D25: pooja535@email.com | E25: Corporate | F25: 2022-01-05 | G25: 2022-01-07 | H25: 2022-01-10 | I25: 3 | J25: West | K25: Maharashtra | L25: Nashik | M25: PRD4565 | N25: Whey Protein 1kg | O25: Sports & Fitness | P25: Nutrition | Q25: Adidas | R25: 3 | S25: 35606.41 | T25: 30 | U25: 74773.46 | V25: 37395.73 | W25: 37377.73 | X25: 49.99 | Y25: 149 | Z25: Cash on Delivery | AA25: Shipped | AB25: No
A26: ORD000025 | B26: CUST8371 | C26: Sunita Mehta | D26: sunita801@email.com | E26: Consumer | F26: 2023-01-08 | G26: 2023-01-09 | H26: 2023-01-17 | I26: 8 | J26: East | K26: West Bengal | L26: Howrah | M26: PRD4391 | N26: Dell Inspiron | O26: Electronics | P26: Laptops | Q26: Penguin | R26: 2 | S26: 42610.17 | T26: 15 | U26: 72437.29 | V26: 43571.21 | W26: 28866.08 | X26: 39.85 | Y26: 99 | Z26: Credit Card | AA26: Delivered | AB26: No | AC26: 1
A27: ORD000026 | B27: CUST4149 | C27: Karan Kumar | D27: karan580@email.com | E27: Consumer | F27: 2022-12-16 | G27: 2022-12-18 | H27: 2022-12-20 | I27: 2 | J27: West | K27: Chhattisgarh | L27: Chhattisgarh | M27: PRD4395 | N27: Palazzo | O27: Clothing | P27: Women | Q27: MuscleBlaze | R27: 5 | S27: 38556.81 | T27: 0 | U27: 192784.05 | V27: 100671.13 | W27: 92112.92 | X27: 47.78 | Y27: 199 | Z27: Cash on Delivery | AA27: Delivered | AB27: No | AC27: 3
A28: ORD000027 | B28: CUST7779 | C28: Kavya Reddy | D28: kavya48@email.com | E28: SMB | F28: 2022-09-11 | G28: 2022-09-13 | H28: 2022-09-18 | I28: 5 | J28: East | K28: Assam | L28: Assam | M28: PRD2944 | N28: MacBook Air | O28: Electronics | P28: Laptops | Q28: HP | R28: 5 | S28: 10249.22 | T28: 30 | U28: 35872.27 | V28: 19954.41 | W28: 15917.86 | X28: 44.37 | Y28: 149 | Z28: Net Banking | AA28: Delivered | AB28: No | AC28: 5
A29: ORD000028 | B29: CUST6377 | C29: Manish Kumar | D29: manish705@email.com | E29: Consumer | F29: 2024-06-24 | G29: 2024-06-26 | H29: 2024-07-03 | I29: 7 | J29: East | K29: Bihar | L29: Bihar | M29: PRD1105 | N29: Fantasy Epic | O29: Books | P29: Fiction | Q29: HP | R29: 1 | S29: 40553.65 | T29: 10 | U29: 36498.29 | V29: 25032.73 | W29: 11465.56 | X29: 31.41 | Y29: 199 | Z29: EMI | AA29: Delivered | AB29: No | AC29: 1
A30: ORD000029 | B30: CUST2403 | C30: Suresh Kumar | D30: suresh379@email.com | E30: Consumer | F30: 2022-11-02 | G30: 2022-11-03 | H30: 2022-11-09 | I30: 6 | J30: East | K30: Bihar | L30: Bihar | M30: PRD4232 | N30: Formal Shirt | O30: Clothing | P30: Men | Q30: Adidas | R30: 5 | S30: 14633.46 | T30: 10 | U30: 65850.57 | V30: 42542.54 | W30: 23308.03 | X30: 35.4 | Y30: 199 | Z30: Net Banking | AA30: Delivered | AB30: No | AC30: 2
A31: ORD000030 | B31: CUST5661 | C31: Kavya Sharma | D31: kavya18@email.com | E31: Home Office | F31: 2022-06-26 | G31: 2022-06-28 | H31: 2022-07-05 | I31: 7 | J31: East | K31: Assam | L31: Assam | M31: PRD2804 | N31: Asus VivoBook | O31: Electronics | P31: Laptops | Q31: Samsung | R31: 5 | S31: 33572.29 | T31: 15 | U31: 142682.23 | V31: 91549.44 | W31: 51132.79 | X31: 35.84 | Y31: 0 | Z31: EMI | AA31: Delivered | AB31: No | AC31: 1
A32: ORD000031 | B32: CUST1608 | C32: Nisha Iyer | D32: nisha950@email.com | E32: SMB | F32: 2022-09-24 | G32: 2022-09-27 | H32: 2022-10-02 | I32: 5 | J32: East | K32: West Bengal | L32: Kolkata | M32: PRD2270 | N32: Lenovo IdeaPad | O32: Electronics | P32: Laptops | Q32: Puma | R32: 3 | S32: 1744.14 | T32: 25 | U32: 3924.32 | V32: 2309.2 | W32: 1615.12 | X32: 41.16 | Y32: 29 | Z32: Cash on Delivery | AA32: Delivered | AB32: No | AC32: 5
A33: ORD000032 | B33: CUST6944 | C33: Amit Patel | D33: amit334@email.com | E33: Consumer | F33: 2024-03-17 | G33: 2024-03-18 | H33: 2024-03-24 | I33: 6 | J33: East | K33: Assam | L33: Assam | M33: PRD2984 | N33: Bookshelf | O33: Home & Kitchen | P33: Furniture | Q33: Amazon Basics | R33: 5 | S33: 47274.41 | T33: 25 | U33: 177279.04 | V33: 89759.23 | W33: 87519.81 | X33: 49.37 | Y33: 199 | Z33: UPI | AA33: Delivered | AB33: No | AC33: 2
A34: ORD000033 | B34: CUST6848 | C34: Rahul Kumar | D34: rahul217@email.com | E34: Consumer | F34: 2024-04-13 | G34: 2024-04-15 | H34: 2024-04-22 | I34: 7 | J34: South | K34: Tamil Nadu | L34: Coimbatore | M34: PRD2119 | N34: HP Pavilion | O34: Electronics | P34: Laptops | Q34: HP | R34: 3 | S34: 32362.85 | T34: 30 | U34: 67961.98 | V34: 43893.72 | W34: 24068.26 | X34: 35.41 | Y34: 199 | Z34: EMI | AA34: Delivered | AB34: No | AC34: 2
A35: ORD000034 | B35: CUST7520 | C35: Nisha Mehta | D35: nisha993@email.com | E35: SMB | F35: 2024-10-25 | G35: 2024-10-27 | H35: 2024-10-30 | I35: 3 | J35: West | K35: Madhya Pradesh | L35: Madhya Pradesh | M35: PRD4929 | N35: Microwave | O35: Home & Kitchen | P35: Appliances | Q35: Samsung | R35: 5 | S35: 18855.16 | T35: 25 | U35: 70706.85 | V35: 39552.18 | W35: 31154.67 | X35: 44.06 | Y35: 149 | Z35: Cash on Delivery | AA35: Delivered | AB35: No
A36: ORD000035 | B36: CUST7057 | C36: Kavya Nair | D36: kavya450@email.com | E36: Corporate | F36: 2024-01-18 | G36: 2024-01-19 | H36: 2024-01-21 | I36: 2 | J36: North | K36: Uttar Pradesh | L36: Lucknow | M36: PRD1457 | N36: Flip Flops | O36: Clothing | P36: Footwear | Q36: HP | R36: 4 | S36: 30156.77 | T36: 25 | U36: 90470.31 | V36: 44797.12 | W36: 45673.19 | X36: 50.48 | Y36: 0 | Z36: Credit Card | AA36: Delivered | AB36: No | AC36: 1
A37: ORD000036 | B37: CUST5589 | C37: Manish Gupta | D37: manish373@email.com | E37: Consumer | F37: 2023-12-28 | G37: 2023-12-30 | H37: 2024-01-07 | I37: 8 | J37: East | K37: Odisha | L37: Odisha | M37: PRD3274 | N37: Realme 11 | O37: Electronics | P37: Smartphones | Q37: Nike | R37: 5 | S37: 25053.9 | T37: 15 | U37: 106479.07 | V37: 52499.91 | W37: 53979.16 | X37: 50.69 | Y37: 29 | Z37: UPI | AA37: Shipped | AB37: No
A38: ORD000037 | B38: CUST8336 | C38: Deepak Singh | D38: deepak90@email.com | E38: SMB | F38: 2023-07-23 | G38: 2023-07-24 | H38: 2023-07-29 | I38: 5 | J38: West | K38: Maharashtra | L38: Pune | M38: PRD2363 | N38: Casual Sneakers | O38: Clothing | P38: Footwear | Q38: Apple | R38: 3 | S38: 38711.63 | T38: 0 | U38: 116134.89 | V38: 79344.42 | W38: 36790.47 | X38: 31.68 | Y38: 0 | Z38: UPI | AA38: Cancelled | AB38: No
A39: ORD000038 | B39: CUST2876 | C39: Anita Singh | D39: anita856@email.com | E39: Corporate | F39: 2022-10-21 | G39: 2022-10-24 | H39: 2022-11-01 | I39: 8 | J39: East | K39: Bihar | L39: Bihar | M39: PRD4817 | N39: Induction Cooktop | O39: Home & Kitchen | P39: Appliances | Q39: HP | R39: 3 | S39: 48428.86 | T39: 25 | U39: 108964.94 | V39: 67002.49 | W39: 41962.45 | X39: 38.51 | Y39: 199 | Z39: EMI | AA39: Delivered | AB39: No
A40: ORD000039 | B40: CUST8786 | C40: Rohit Singh | D40: rohit687@email.com | E40: SMB | F40: 2023-01-29 | G40: 2023-01-31 | H40: 2023-02-03 | I40: 3 | J40: West | K40: Chhattisgarh | L40: Chhattisgarh | M40: PRD1009 | N40: Artificial Plant | O40: Home & Kitchen | P40: Decor | Q40: Adidas | R40: 4 | S40: 6795.1 | T40: 20 | U40: 21744.32 | V40: 10814.27 | W40: 10930.05 | X40: 50.27 | Y40: 149 | Z40: EMI | AA40: Delivered | AB40: No | AC40: 1
A41: ORD000040 | B41: CUST4235 | C41: Priya Nair | D41: priya147@email.com | E41: SMB | F41: 2023-01-25 | G41: 2023-01-27 | H41: 2023-01-30 | I41: 3 | J41: West | K41: Goa | L41: Goa | M41: PRD3948 | N41: Bookshelf | O41: Home & Kitchen | P41: Furniture | Q41: Wiley | R41: 3 | S41: 219.93 | T41: 5 | U41: 626.8 | V41: 350.28 | W41: 276.52 | X41: 44.12 | Y41: 0 | Z41: Credit Card | AA41: Delivered | AB41: No
A42: ORD000041 | B42: CUST7025 | C42: Priya Kumar | D42: priya412@email.com | E42: Consumer | F42: 2022-09-29 | G42: 2022-10-02 | H42: 2022-10-06 | I42: 4 | J42: North | K42: Uttar Pradesh | L42: Kanpur | M42: PRD3091 | N42: Microwave | O42: Home & Kitchen | P42: Appliances | Q42: Dell | R42: 1 | S42: 42131.17 | T42: 20 | U42: 33704.94 | V42: 20787.63 | W42: 12917.31 | X42: 38.32 | Y42: 49 | Z42: Debit Card | AA42: Shipped | AB42: No
A43: ORD000042 | B43: CUST7663 | C43: Suresh Verma | D43: suresh482@email.com | E43: Corporate | F43: 2023-01-13 | G43: 2023-01-16 | H43: 2023-01-22 | I43: 6 | J43: South | K43: Karnataka | L43: Mysuru | M43: PRD2848 | N43: Kurta Set | O43: Clothing | P43: Women | Q43: OnePlus | R43: 4 | S43: 9447.96 | T43: 10 | U43: 34012.66 | V43: 15583.06 | W43: 18429.6 | X43: 54.18 | Y43: 199 | Z43: Credit Card | AA43: Delivered | AB43: No | AC43: 1
A44: ORD000043 | B44: CUST8312 | C44: Manish Nair | D44: manish656@email.com | E44: SMB | F44: 2024-11-03 | G44: 2024-11-06 | H44: 2024-11-14 | I44: 8 | J44: South | K44: Tamil Nadu | L44: Coimbatore | M44: PRD4082 | N44: Crop Top | O44: Clothing | P44: Women | Q44: MuscleBlaze | R44: 4 | S44: 21976.36 | T44: 15 | U44: 74719.62 | V44: 50101.16 | W44: 24618.46 | X44: 32.95 | Y44: 49 | Z44: Debit Card | AA44: Delivered | AB44: No | AC44: 4
A45: ORD000044 | B45: CUST1074 | C45: Deepak Iyer | D45: deepak932@email.com | E45: Home Office | F45: 2022-11-18 | G45: 2022-11-21 | H45: 2022-11-29 | I45: 8 | J45: South | K45: Andhra Pradesh | L45: Andhra Pradesh | M45: PRD1941 | N45: Artificial Plant | O45: Home & Kitchen | P45: Decor | Q45: Realme | R45: 1 | S45: 10102.63 | T45: 15 | U45: 8587.24 | V45: 4608.3 | W45: 3978.94 | X45: 46.34 | Y45: 99 | Z45: Net Banking | AA45: Cancelled | AB45: No
A46: ORD000045 | B46: CUST9749 | C46: Manish Kumar | D46: manish227@email.com | E46: Corporate | F46: 2022-08-08 | G46: 2022-08-10 | H46: 2022-08-15 | I46: 5 | J46: West | K46: Madhya Pradesh | L46: Madhya Pradesh | M46: PRD1817 | N46: Denim Jeans | O46: Clothing | P46: Men | Q46: Apple | R46: 4 | S46: 6215.95 | T46: 25 | U46: 18647.85 | V46: 11707.31 | W46: 6940.54 | X46: 37.22 | Y46: 29 | Z46: UPI | AA46: Delivered | AB46: No | AC46: 1
A47: ORD000046 | B47: CUST9659 | C47: Karan Mehta | D47: karan857@email.com | E47: Home Office | F47: 2022-10-04 | G47: 2022-10-07 | H47: 2022-10-09 | I47: 2 | J47: East | K47: West Bengal | L47: Siliguri | M47: PRD4911 | N47: Realme 11 | O47: Electronics | P47: Smartphones | Q47: Nike | R47: 3 | S47: 27050.52 | T47: 0 | U47: 81151.56 | V47: 39713.94 | W47: 41437.62 | X47: 51.06 | Y47: 99 | Z47: Credit Card | AA47: Cancelled | AB47: No
A48: ORD000047 | B48: CUST1201 | C48: Arjun Nair | D48: arjun513@email.com | E48: SMB | F48: 2023-06-17 | G48: 2023-06-18 | H48: 2023-06-26 | I48: 8 | J48: North | K48: Delhi | L48: Noida | M48: PRD4465 | N48: Wall Clock | O48: Home & Kitchen | P48: Decor | Q48: Prestige | R48: 4 | S48: 27231.66 | T48: 0 | U48: 108926.64 | V48: 58806.21 | W48: 50120.43 | X48: 46.01 | Y48: 29 | Z48: Credit Card | AA48: Delivered | AB48: No | AC48: 3
A49: ORD000048 | B49: CUST3398 | C49: Priya Sharma | D49: priya890@email.com | E49: SMB | F49: 2023-09-29 | G49: 2023-10-01 | H49: 2023-10-07 | I49: 6 | J49: South | K49: Kerala | L49: Thiruvananthapuram | M49: PRD4938 | N49: Asus VivoBook | O49: Electronics | P49: Laptops | Q49: Samsung | R49: 2 | S49: 20549.38 | T49: 25 | U49: 30824.07 | V49: 15216.22 | W49: 15607.85 | X49: 50.64 | Y49: 29 | Z49: EMI | AA49: Delivered | AB49: No | AC49: 5
A50: ORD000049 | B50: CUST8825 | C50: Rekha Sharma | D50: rekha658@email.com | E50: Home Office | F50: 2024-10-13 | G50: 2024-10-16 | H50: 2024-10-18 | I50: 2 | J50: North | K50: Uttar Pradesh | L50: Agra | M50: PRD1753 | N50: HP Pavilion | O50: Electronics | P50: Laptops | Q50: Apple | R50: 1 | S50: 26491.84 | T50: 0 | U50: 26491.84 | V50: 12433.86 | W50: 14057.98 | X50: 53.07 | Y50: 99 | Z50: Digital Wallet | AA50: Delivered | AB50: No
A51: ORD000050 | B51: CUST9609 | C51: Pooja Verma | D51: pooja703@email.com | E51: SMB | F51: 2022-12-02 | G51: 2022-12-03 | H51: 2022-12-07 | I51: 4 | J51: West | K51: Chhattisgarh | L51: Chhattisgarh | M51: PRD1338 | N51: Self-Help Guide | O51: Books | P51: Non-Fiction | Q51: Puma | R51: 2 | S51: 20966.45 | T51: 0 | U51: 41932.9 | V51: 26866.41 | W51: 15066.49 | X51: 35.93 | Y51: 149 | Z51: Debit Card | AA51: Delivered | AB51: No
A52: ORD000051 | B52: CUST9068 | C52: Rohit Singh | D52: rohit293@email.com | E52: Home Office | F52: 2024-03-12 | G52: 2024-03-13 | H52: 2024-03-18 | I52: 5 | J52: South | K52: Andhra Pradesh | L52: Andhra Pradesh | M52: PRD4656 | N52: Running Shoes | O52: Clothing | P52: Footwear | Q52: Prestige | R52: 2 | S52: 1357 | T52: 0 | U52: 2714 | V52: 1452.86 | W52: 1261.14 | X52: 46.47 | Y52: 199 | Z52: EMI | AA52: Shipped | AB52: No
A53: ORD000052 | B53: CUST1609 | C53: Rohit Reddy | D53: rohit115@email.com | E53: Home Office | F53: 2023-03-01 | G53: 2023-03-02 | H53: 2023-03-05 | I53: 3 | J53: West | K53: Chhattisgarh | L53: Chhattisgarh | M53: PRD3427 | N53: Samsung S24 | O53: Electronics | P53: Smartphones | Q53: Adidas | R53: 2 | S53: 26670.82 | T53: 10 | U53: 48007.48 | V53: 32876.54 | W53: 15130.94 | X53: 31.52 | Y53: 29 | Z53: EMI | AA53: Delivered | AB53: No | AC53: 2
A54: ORD000053 | B54: CUST5417 | C54: Nisha Patel | D54: nisha772@email.com | E54: SMB | F54: 2023-07-04 | G54: 2023-07-06 | H54: 2023-07-12 | I54: 6 | J54: South | K54: Andhra Pradesh | L54: Andhra Pradesh | M54: PRD1887 | N54: Personal Finance | O54: Books | P54: Non-Fiction | Q54: Realme | R54: 1 | S54: 25317.7 | T54: 15 | U54: 21520.04 | V54: 13920.3 | W54: 7599.74 | X54: 35.31 | Y54: 49 | Z54: Net Banking | AA54: Delivered | AB54: No | AC54: 5
A55: ORD000054 | B55: CUST1888 | C55: Pooja Gupta | D55: pooja750@email.com | E55: Corporate | F55: 2023-05-15 | G55: 2023-05-18 | H55: 2023-05-23 | I55: 5 | J55: West | K55: Chhattisgarh | L55: Chhattisgarh | M55: PRD1473 | N55: Personal Finance | O55: Books | P55: Non-Fiction | Q55: Philips | R55: 3 | S55: 32433.78 | T55: 10 | U55: 87571.21 | V55: 57612.64 | W55: 29958.57 | X55: 34.21 | Y55: 49 | Z55: Net Banking | AA55: Delivered | AB55: Yes
A56: ORD000055 | B56: CUST6118 | C56: Suresh Kumar | D56: suresh416@email.com | E56: Consumer | F56: 2024-02-07 | G56: 2024-02-10 | H56: 2024-02-15 | I56: 5 | J56: South | K56: Karnataka | L56: Mangaluru | M56: PRD1371 | N56: OnePlus 12 | O56: Electronics | P56: Smartphones | Q56: Prestige | R56: 5 | S56: 168.12 | T56: 5 | U56: 798.57 | V56: 401.18 | W56: 397.39 | X56: 49.76 | Y56: 0 | Z56: Cash on Delivery | AA56: Delivered | AB56: No
A57: ORD000056 | B57: CUST4714 | C57: Sunita Nair | D57: sunita237@email.com | E57: Consumer | F57: 2023-03-01 | G57: 2023-03-02 | H57: 2023-03-07 | I57: 5 | J57: South | K57: Tamil Nadu | L57: Coimbatore | M57: PRD2552 | N57: Bomber Jacket | O57: Clothing | P57: Men | Q57: OnePlus | R57: 2 | S57: 40482.14 | T57: 15 | U57: 68819.64 | V57: 31907.51 | W57: 36912.13 | X57: 53.64 | Y57: 149 | Z57: UPI | AA57: Shipped | AB57: No
A58: ORD000057 | B58: CUST6930 | C58: Priya Sharma | D58: priya30@email.com | E58: Consumer | F58: 2023-08-28 | G58: 2023-08-30 | H58: 2023-09-04 | I58: 5 | J58: East | K58: West Bengal | L58: Siliguri | M58: PRD3449 | N58: T-Shirt | O58: Clothing | P58: Men | Q58: Samsung | R58: 1 | S58: 23794.17 | T58: 25 | U58: 17845.63 | V58: 10033.16 | W58: 7812.47 | X58: 43.78 | Y58: 149 | Z58: EMI | AA58: Cancelled | AB58: No
A59: ORD000058 | B59: CUST2792 | C59: Rohit Singh | D59: rohit246@email.com | E59: Consumer | F59: 2024-01-26 | G59: 2024-01-27 | H59: 2024-02-01 | I59: 5 | J59: North | K59: Delhi | L59: Noida | M59: PRD1614 | N59: Business Strategy | O59: Books | P59: Non-Fiction | Q59: Philips | R59: 3 | S59: 7907.02 | T59: 15 | U59: 20162.9 | V59: 14102.66 | W59: 6060.24 | X59: 30.06 | Y59: 49 | Z59: EMI | AA59: Shipped | AB59: No
A60: ORD000059 | B60: CUST5931 | C60: Manish Sharma | D60: manish594@email.com | E60: Consumer | F60: 2022-12-10 | G60: 2022-12-11 | H60: 2022-12-15 | I60: 4 | J60: South | K60: Andhra Pradesh | L60: Andhra Pradesh | M60: PRD2504 | N60: Bestseller Novel | O60: Books | P60: Fiction | Q60: Nike | R60: 4 | S60: 16360.34 | T60: 15 | U60: 55625.16 | V60: 25333.12 | W60: 30292.04 | X60: 54.46 | Y60: 49 | Z60: Net Banking | AA60: Cancelled | AB60: No
A61: ORD000060 | B61: CUST8611 | C61: Priya Mehta | D61: priya967@email.com | E61: Consumer | F61: 2023-12-14 | G61: 2023-12-15 | H61: 2023-12-20 | I61: 5 | J61: North | K61: Punjab | L61: Punjab | M61: PRD2642 | N61: Denim Jeans | O61: Clothing | P61: Men | Q61: Amazon Basics | R61: 4 | S61: 43193.97 | T61: 20 | U61: 138220.7 | V61: 94334.53 | W61: 43886.17 | X61: 31.75 | Y61: 99 | Z61: Digital Wallet | AA61: Returned | AB61: Yes
A62: ORD000061 | B62: CUST4552 | C62: Manish Nair | D62: manish77@email.com | E62: Corporate | F62: 2023-08-23 | G62: 2023-08-26 | H62: 2023-09-03 | I62: 8 | J62: South | K62: Karnataka | L62: Mysuru | M62: PRD2817 | N62: Dell Inspiron | O62: Electronics | P62: Laptops | Q62: Apple | R62: 1 | S62: 12940.01 | T62: 25 | U62: 9705.01 | V62: 5005.59 | W62: 4699.42 | X62: 48.42 | Y62: 29 | Z62: UPI | AA62: Delivered | AB62: No | AC62: 3
A63: ORD000062 | B63: CUST2487 | C63: Arjun Sharma | D63: arjun956@email.com | E63: SMB | F63: 2023-12-22 | G63: 2023-12-24 | H63: 2023-12-31 | I63: 7 | J63: West | K63: Goa | L63: Goa | M63: PRD2651 | N63: Yoga Mat | O63: Sports & Fitness | P63: Equipment | Q63: Nike | R63: 5 | S63: 16092.76 | T63: 10 | U63: 72417.42 | V63: 44439.93 | W63: 27977.49 | X63: 38.63 | Y63: 149 | Z63: UPI | AA63: Processing | AB63: No
A64: ORD000063 | B64: CUST5004 | C64: Meena Patel | D64: meena988@email.com | E64: Home Office | F64: 2022-07-05 | G64: 2022-07-08 | H64: 2022-07-14 | I64: 6 | J64: West | K64: Maharashtra | L64: Pune | M64: PRD2925 | N64: iPhone 15 | O64: Electronics | P64: Smartphones | Q64: Apple | R64: 1 | S64: 33621.55 | T64: 15 | U64: 28578.32 | V64: 14383.59 | W64: 14194.73 | X64: 49.67 | Y64: 29 | Z64: Cash on Delivery | AA64: Delivered | AB64: No
A65: ORD000064 | B65: CUST3433 | C65: Rahul Gupta | D65: rahul873@email.com | E65: Home Office | F65: 2023-10-12 | G65: 2023-10-14 | H65: 2023-10-22 | I65: 8 | J65: West | K65: Goa | L65: Goa | M65: PRD1307 | N65: Mixer Grinder | O65: Home & Kitchen | P65: Appliances | Q65: Apple | R65: 5 | S65: 3238.06 | T65: 30 | U65: 11333.21 | V65: 7514.16 | W65: 3819.05 | X65: 33.7 | Y65: 199 | Z65: UPI | AA65: Delivered | AB65: No | AC65: 4
A66: ORD000065 | B66: CUST3079 | C66: Deepak Mehta | D66: deepak235@email.com | E66: Consumer | F66: 2023-10-12 | G66: 2023-10-14 | H66: 2023-10-21 | I66: 7 | J66: West | K66: Goa | L66: Goa | M66: PRD3638 | N66: Wall Clock | O66: Home & Kitchen | P66: Decor | Q66: HP | R66: 1 | S66: 41818.98 | T66: 10 | U66: 37637.08 | V66: 25203.05 | W66: 12434.03 | X66: 33.04 | Y66: 99 | Z66: Net Banking | AA66: Delivered | AB66: No | AC66: 1
A67: ORD000066 | B67: CUST7923 | C67: Karan Singh | D67: karan401@email.com | E67: Home Office | F67: 2023-12-14 | G67: 2023-12-15 | H67: 2023-12-22 | I67: 7 | J67: East | K67: Odisha | L67: Odisha | M67: PRD1601 | N67: MacBook Air | O67: Electronics | P67: Laptops | Q67: HP | R67: 4 | S67: 2787.97 | T67: 20 | U67: 8921.5 | V67: 5813.9 | W67: 3107.6 | X67: 34.83 | Y67: 149 | Z67: UPI | AA67: Shipped | AB67: No
A68: ORD000067 | B68: CUST4492 | C68: Manish Sharma | D68: manish488@email.com | E68: Consumer | F68: 2023-10-07 | G68: 2023-10-08 | H68: 2023-10-13 | I68: 5 | J68: West | K68: Goa | L68: Goa | M68: PRD4814 | N68: Study Table | O68: Home & Kitchen | P68: Furniture | Q68: Penguin | R68: 2 | S68: 4972.55 | T68: 15 | U68: 8453.34 | V68: 5393.36 | W68: 3059.98 | X68: 36.2 | Y68: 49 | Z68: Credit Card | AA68: Delivered | AB68: No
A69: ORD000068 | B69: CUST9632 | C69: Sunita Kumar | D69: sunita233@email.com | E69: Consumer | F69: 2024-05-27 | G69: 2024-05-30 | H69: 2024-06-07 | I69: 8 | J69: East | K69: Jharkhand | L69: Jharkhand | M69: PRD2123 | N69: TWS Earbuds | O69: Electronics | P69: Accessories | Q69: Adidas | R69: 5 | S69: 29951.15 | T69: 25 | U69: 112316.81 | V69: 51820.53 | W69: 60496.28 | X69: 53.86 | Y69: 99 | Z69: UPI | AA69: Delivered | AB69: No
A70: ORD000069 | B70: CUST9224 | C70: Suresh Nair | D70: suresh791@email.com | E70: Home Office | F70: 2024-08-18 | G70: 2024-08-19 | H70: 2024-08-24 | I70: 5 | J70: East | K70: Bihar | L70: Bihar | M70: PRD1639 | N70: Health & Fitness | O70: Books | P70: Non-Fiction | Q70: Realme | R70: 2 | S70: 13409.86 | T70: 5 | U70: 25478.73 | V70: 13829.34 | W70: 11649.39 | X70: 45.72 | Y70: 199 | Z70: Digital Wallet | AA70: Shipped | AB70: No
A71: ORD000070 | B71: CUST1292 | C71: Meena Singh | D71: meena756@email.com | E71: Home Office | F71: 2022-08-25 | G71: 2022-08-28 | H71: 2022-09-01 | I71: 4 | J71: East | K71: Odisha | L71: Odisha | M71: PRD1692 | N71: Self-Help Guide | O71: Books | P71: Non-Fiction | Q71: HP | R71: 1 | S71: 39768.38 | T71: 5 | U71: 37779.96 | V71: 21475.72 | W71: 16304.24 | X71: 43.16 | Y71: 0 | Z71: Cash on Delivery | AA71: Delivered | AB71: No | AC71: 5
A72: ORD000071 | B72: CUST3816 | C72: Aditya Iyer | D72: aditya295@email.com | E72: Consumer | F72: 2022-11-10 | G72: 2022-11-12 | H72: 2022-11-17 | I72: 5 | J72: North | K72: Haryana | L72: Haryana | M72: PRD2744 | N72: Phone Case | O72: Electronics | P72: Accessories | Q72: Adidas | R72: 5 | S72: 7700.4 | T72: 0 | U72: 38502 | V72: 22433.55 | W72: 16068.45 | X72: 41.73 | Y72: 99 | Z72: EMI | AA72: Delivered | AB72: No | AC72: 4
A73: ORD000072 | B73: CUST9229 | C73: Rahul Nair | D73: rahul819@email.com | E73: Corporate | F73: 2022-02-23 | G73: 2022-02-26 | H73: 2022-03-04 | I73: 6 | J73: North | K73: Delhi | L73: Gurgaon | M73: PRD1364 | N73: Ergonomic Chair | O73: Home & Kitchen | P73: Furniture | Q73: Penguin | R73: 4 | S73: 8916.21 | T73: 15 | U73: 30315.11 | V73: 17528.19 | W73: 12786.92 | X73: 42.18 | Y73: 149 | Z73: Digital Wallet | AA73: Returned | AB73: Yes
A74: ORD000073 | B74: CUST1037 | C74: Pooja Patel | D74: pooja845@email.com | E74: Corporate | F74: 2023-03-06 | G74: 2023-03-07 | H74: 2023-03-09 | I74: 2 | J74: North | K74: Uttar Pradesh | L74: Kanpur | M74: PRD3126 | N74: MacBook Air | O74: Electronics | P74: Laptops | Q74: Dell | R74: 5 | S74: 7020.24 | T74: 20 | U74: 28080.96 | V74: 13679.08 | W74: 14401.88 | X74: 51.29 | Y74: 29 | Z74: Digital Wallet | AA74: Delivered | AB74: No | AC74: 2
A75: ORD000074 | B75: CUST9059 | C75: Aditya Reddy | D75: aditya239@email.com | E75: SMB | F75: 2022-12-24 | G75: 2022-12-26 | H75: 2023-01-02 | I75: 7 | J75: East | K75: Jharkhand | L75: Jharkhand | M75: PRD4534 | N75: Short Story Collection | O75: Books | P75: Fiction | Q75: Amazon Basics | R75: 1 | S75: 47900.77 | T75: 10 | U75: 43110.69 | V75: 20390.59 | W75: 22720.1 | X75: 52.7 | Y75: 49 | Z75: Debit Card | AA75: Shipped | AB75: No
A76: ORD000075 | B76: CUST5710 | C76: Vikram Iyer | D76: vikram147@email.com | E76: Home Office | F76: 2024-09-12 | G76: 2024-09-14 | H76: 2024-09-16 | I76: 2 | J76: South | K76: Karnataka | L76: Mangaluru | M76: PRD1206 | N76: Wall Clock | O76: Home & Kitchen | P76: Decor | Q76: Samsung | R76: 5 | S76: 12668.9 | T76: 0 | U76: 63344.5 | V76: 35461.63 | W76: 27882.87 | X76: 44.02 | Y76: 29 | Z76: Digital Wallet | AA76: Delivered | AB76: No | AC76: 5
A77: ORD000076 | B77: CUST5839 | C77: Karan Nair | D77: karan688@email.com | E77: Corporate | F77: 2024-10-03 | G77: 2024-10-05 | H77: 2024-10-11 | I77: 6 | J77: East | K77: Assam | L77: Assam | M77: PRD3001 | N77: Mixer Grinder | O77: Home & Kitchen | P77: Appliances | Q77: Wiley | R77: 5 | S77: 18238.6 | T77: 25 | U77: 68394.75 | V77: 45283.93 | W77: 23110.82 | X77: 33.79 | Y77: 199 | Z77: Credit Card | AA77: Processing | AB77: No
A78: ORD000077 | B78: CUST4399 | C78: Suresh Sharma | D78: suresh52@email.com | E78: Consumer | F78: 2022-09-19 | G78: 2022-09-22 | H78: 2022-09-25 | I78: 3 | J78: West | K78: Chhattisgarh | L78: Chhattisgarh | M78: PRD1120 | N78: Crime Thriller | O78: Books | P78: Fiction | Q78: Puma | R78: 1 | S78: 21142.66 | T78: 25 | U78: 15856.99 | V78: 10247.09 | W78: 5609.9 | X78: 35.38 | Y78: 0 | Z78: Net Banking | AA78: Delivered | AB78: No | AC78: 1
A79: ORD000078 | B79: CUST1546 | C79: Rohit Verma | D79: rohit572@email.com | E79: SMB | F79: 2022-08-01 | G79: 2022-08-02 | H79: 2022-08-05 | I79: 3 | J79: East | K79: Odisha | L79: Odisha | M79: PRD4216 | N79: OnePlus 12 | O79: Electronics | P79: Smartphones | Q79: Nike | R79: 5 | S79: 13982.02 | T79: 20 | U79: 55928.08 | V79: 36804.67 | W79: 19123.41 | X79: 34.19 | Y79: 49 | Z79: Credit Card | AA79: Delivered | AB79: No | AC79: 1
A80: ORD000079 | B80: CUST4044 | C80: Karan Sharma | D80: karan144@email.com | E80: SMB | F80: 2024-06-19 | G80: 2024-06-22 | H80: 2024-06-25 | I80: 3 | J80: East | K80: Jharkhand | L80: Jharkhand | M80: PRD3660 | N80: BCAA Powder | O80: Sports & Fitness | P80: Nutrition | Q80: Prestige | R80: 1 | S80: 12465.16 | T80: 0 | U80: 12465.16 | V80: 8675.69 | W80: 3789.47 | X80: 30.4 | Y80: 49 | Z80: UPI | AA80: Delivered | AB80: No | AC80: 3
A81: ORD000080 | B81: CUST4233 | C81: Karan Mehta | D81: karan455@email.com | E81: Home Office | F81: 2023-09-10 | G81: 2023-09-12 | H81: 2023-09-19 | I81: 7 | J81: North | K81: Rajasthan | L81: Udaipur | M81: PRD3662 | N81: Kurta Set | O81: Clothing | P81: Women | Q81: Dell | R81: 1 | S81: 31248.52 | T81: 0 | U81: 31248.52 | V81: 21291.24 | W81: 9957.28 | X81: 31.86 | Y81: 149 | Z81: Net Banking | AA81: Delivered | AB81: No
A82: ORD000081 | B82: CUST6257 | C82: Pooja Kumar | D82: pooja936@email.com | E82: Corporate | F82: 2023-09-20 | G82: 2023-09-22 | H82: 2023-09-26 | I82: 4 | J82: South | K82: Andhra Pradesh | L82: Andhra Pradesh | M82: PRD4761 | N82: Samsung S24 | O82: Electronics | P82: Smartphones | Q82: Adidas | R82: 1 | S82: 33573.61 | T82: 20 | U82: 26858.89 | V82: 13876.53 | W82: 12982.36 | X82: 48.34 | Y82: 29 | Z82: Debit Card | AA82: Delivered | AB82: No
A83: ORD000082 | B83: CUST3232 | C83: Priya Kumar | D83: priya747@email.com | E83: Home Office | F83: 2023-01-02 | G83: 2023-01-05 | H83: 2023-01-12 | I83: 7 | J83: East | K83: Assam | L83: Assam | M83: PRD3015 | N83: Palazzo | O83: Clothing | P83: Women | Q83: Amazon Basics | R83: 1 | S83: 33373.45 | T83: 30 | U83: 23361.41 | V83: 13498.07 | W83: 9863.34 | X83: 42.22 | Y83: 199 | Z83: Net Banking | AA83: Shipped | AB83: No
A84: ORD000083 | B84: CUST1264 | C84: Rahul Gupta | D84: rahul391@email.com | E84: SMB | F84: 2022-07-25 | G84: 2022-07-27 | H84: 2022-08-04 | I84: 8 | J84: South | K84: Telangana | L84: Nizamabad | M84: PRD2704 | N84: Engineering Math | O84: Books | P84: Education | Q84: Realme | R84: 4 | S84: 3554.04 | T84: 10 | U84: 12794.54 | V84: 7120.7 | W84: 5673.84 | X84: 44.35 | Y84: 49 | Z84: EMI | AA84: Processing | AB84: No
A85: ORD000084 | B85: CUST9029 | C85: Arjun Iyer | D85: arjun211@email.com | E85: Consumer | F85: 2022-07-11 | G85: 2022-07-12 | H85: 2022-07-18 | I85: 6 | J85: West | K85: Maharashtra | L85: Nashik | M85: PRD4444 | N85: Crime Thriller | O85: Books | P85: Fiction | Q85: Apple | R85: 1 | S85: 28674.88 | T85: 0 | U85: 28674.88 | V85: 18055.38 | W85: 10619.5 | X85: 37.03 | Y85: 199 | Z85: Credit Card | AA85: Delivered | AB85: No | AC85: 1
A86: ORD000085 | B86: CUST5698 | C86: Amit Kumar | D86: amit942@email.com | E86: Home Office | F86: 2023-03-09 | G86: 2023-03-10 | H86: 2023-03-15 | I86: 5 | J86: East | K86: West Bengal | L86: Kolkata | M86: PRD3119 | N86: Biography | O86: Books | P86: Non-Fiction | Q86: Apple | R86: 4 | S86: 470.64 | T86: 5 | U86: 1788.43 | V86: 1021.93 | W86: 766.5 | X86: 42.86 | Y86: 199 | Z86: Credit Card | AA86: Delivered | AB86: No
A87: ORD000086 | B87: CUST1993 | C87: Anita Reddy | D87: anita787@email.com | E87: SMB | F87: 2024-06-02 | G87: 2024-06-05 | H87: 2024-06-09 | I87: 4 | J87: North | K87: Punjab | L87: Punjab | M87: PRD4870 | N87: HP Pavilion | O87: Electronics | P87: Laptops | Q87: Wiley | R87: 3 | S87: 22465.86 | T87: 25 | U87: 50548.18 | V87: 26519.71 | W87: 24028.47 | X87: 47.54 | Y87: 49 | Z87: Debit Card | AA87: Cancelled | AB87: No
A88: ORD000087 | B88: CUST4836 | C88: Swati Iyer | D88: swati322@email.com | E88: Home Office | F88: 2022-11-22 | G88: 2022-11-25 | H88: 2022-12-02 | I88: 7 | J88: South | K88: Andhra Pradesh | L88: Andhra Pradesh | M88: PRD1045 | N88: Wall Clock | O88: Home & Kitchen | P88: Decor | Q88: Nike | R88: 4 | S88: 31232.37 | T88: 0 | U88: 124929.48 | V88: 60259.29 | W88: 64670.19 | X88: 51.77 | Y88: 99 | Z88: Cash on Delivery | AA88: Delivered | AB88: No
A89: ORD000088 | B89: CUST1909 | C89: Rahul Reddy | D89: rahul949@email.com | E89: Home Office | F89: 2022-06-12 | G89: 2022-06-15 | H89: 2022-06-20 | I89: 5 | J89: North | K89: Rajasthan | L89: Udaipur | M89: PRD4703 | N89: Engineering Math | O89: Books | P89: Education | Q89: HP | R89: 3 | S89: 21799.99 | T89: 25 | U89: 49049.98 | V89: 27550.13 | W89: 21499.85 | X89: 43.83 | Y89: 199 | Z89: UPI | AA89: Delivered | AB89: No | AC89: 2
A90: ORD000089 | B90: CUST5218 | C90: Arjun Sharma | D90: arjun885@email.com | E90: Consumer | F90: 2023-10-10 | G90: 2023-10-13 | H90: 2023-10-20 | I90: 7 | J90: East | K90: Bihar | L90: Bihar | M90: PRD2241 | N90: Self-Help Guide | O90: Books | P90: Non-Fiction | Q90: Prestige | R90: 2 | S90: 2472.74 | T90: 25 | U90: 3709.11 | V90: 2034.04 | W90: 1675.07 | X90: 45.16 | Y90: 99 | Z90: Digital Wallet | AA90: Delivered | AB90: No | AC90: 1
A91: ORD000090 | B91: CUST5813 | C91: Rahul Kumar | D91: rahul39@email.com | E91: Consumer | F91: 2024-06-06 | G91: 2024-06-08 | H91: 2024-06-12 | I91: 4 | J91: North | K91: Haryana | L91: Haryana | M91: PRD2199 | N91: IELTS Practice | O91: Books | P91: Education | Q91: Samsung | R91: 5 | S91: 3654.44 | T91: 10 | U91: 16444.98 | V91: 10621.11 | W91: 5823.87 | X91: 35.41 | Y91: 49 | Z91: EMI | AA91: Delivered | AB91: Yes
A92: ORD000091 | B92: CUST3326 | C92: Swati Iyer | D92: swati881@email.com | E92: Home Office | F92: 2024-06-21 | G92: 2024-06-23 | H92: 2024-06-26 | I92: 3 | J92: West | K92: Goa | L92: Goa | M92: PRD2623 | N92: Curtain Set | O92: Home & Kitchen | P92: Decor | Q92: Nike | R92: 5 | S92: 39607.14 | T92: 10 | U92: 178232.13 | V92: 112811.89 | W92: 65420.24 | X92: 36.71 | Y92: 149 | Z92: Net Banking | AA92: Delivered | AB92: Yes | AC92: 4
A93: ORD000092 | B93: CUST3898 | C93: Suresh Nair | D93: suresh698@email.com | E93: Home Office | F93: 2022-06-12 | G93: 2022-06-13 | H93: 2022-06-19 | I93: 6 | J93: South | K93: Telangana | L93: Warangal | M93: PRD1245 | N93: Bestseller Novel | O93: Books | P93: Fiction | Q93: Realme | R93: 5 | S93: 2024.16 | T93: 15 | U93: 8602.68 | V93: 5166.85 | W93: 3435.83 | X93: 39.94 | Y93: 199 | Z93: Cash on Delivery | AA93: Delivered | AB93: No | AC93: 2
A94: ORD000093 | B94: CUST7345 | C94: Pooja Gupta | D94: pooja900@email.com | E94: Corporate | F94: 2024-10-15 | G94: 2024-10-17 | H94: 2024-10-19 | I94: 2 | J94: North | K94: Haryana | L94: Haryana | M94: PRD4352 | N94: Badminton Racket | O94: Sports & Fitness | P94: Equipment | Q94: Realme | R94: 1 | S94: 16943.01 | T94: 0 | U94: 16943.01 | V94: 9484.66 | W94: 7458.35 | X94: 44.02 | Y94: 0 | Z94: Digital Wallet | AA94: Delivered | AB94: No | AC94: 5
A95: ORD000094 | B95: CUST7871 | C95: Manish Singh | D95: manish290@email.com | E95: Home Office | F95: 2023-09-22 | G95: 2023-09-24 | H95: 2023-09-26 | I95: 2 | J95: North | K95: Delhi | L95: Gurgaon | M95: PRD4117 | N95: Denim Jeans | O95: Clothing | P95: Men | Q95: Apple | R95: 5 | S95: 22955.4 | T95: 15 | U95: 97560.45 | V95: 45314.65 | W95: 52245.8 | X95: 53.55 | Y95: 49 | Z95: EMI | AA95: Delivered | AB95: No | AC95: 3
A96: ORD000095 | B96: CUST3574 | C96: Deepak Gupta | D96: deepak800@email.com | E96: SMB | F96: 2023-05-11 | G96: 2023-05-13 | H96: 2023-05-20 | I96: 7 | J96: South | K96: Telangana | L96: Nizamabad | M96: PRD4064 | N96: Water Purifier | O96: Home & Kitchen | P96: Appliances | Q96: Realme | R96: 2 | S96: 25449 | T96: 30 | U96: 35628.6 | V96: 16632.42 | W96: 18996.18 | X96: 53.32 | Y96: 0 | Z96: EMI | AA96: Delivered | AB96: No | AC96: 5
A97: ORD000096 | B97: CUST4844 | C97: Deepak Nair | D97: deepak904@email.com | E97: Corporate | F97: 2023-09-26 | G97: 2023-09-28 | H97: 2023-10-02 | I97: 4 | J97: East | K97: Assam | L97: Assam | M97: PRD3639 | N97: Sofa Set | O97: Home & Kitchen | P97: Furniture | Q97: MuscleBlaze | R97: 5 | S97: 49623.05 | T97: 0 | U97: 248115.25 | V97: 166799.84 | W97: 81315.41 | X97: 32.77 | Y97: 149 | Z97: EMI | AA97: Cancelled | AB97: No
A98: ORD000097 | B98: CUST6269 | C98: Meena Mehta | D98: meena255@email.com | E98: Home Office | F98: 2024-05-06 | G98: 2024-05-08 | H98: 2024-05-16 | I98: 8 | J98: East | K98: Assam | L98: Assam | M98: PRD4508 | N98: Yoga Mat | O98: Sports & Fitness | P98: Equipment | Q98: Penguin | R98: 2 | S98: 23947.01 | T98: 25 | U98: 35920.51 | V98: 21898.94 | W98: 14021.57 | X98: 39.03 | Y98: 99 | Z98: Credit Card | AA98: Delivered | AB98: No
A99: ORD000098 | B99: CUST2337 | C99: Sunita Kumar | D99: sunita603@email.com | E99: Consumer | F99: 2024-06-23 | G99: 2024-06-25 | H99: 2024-07-03 | I99: 8 | J99: East | K99: West Bengal | L99: Siliguri | M99: PRD3463 | N99: Fast Charger | O99: Electronics | P99: Accessories | Q99: Apple | R99: 4 | S99: 6383.49 | T99: 20 | U99: 20427.17 | V99: 12111.52 | W99: 8315.65 | X99: 40.71 | Y99: 49 | Z99: Credit Card | AA99: Delivered | AB99: No | AC99: 5
A100: ORD000099 | B100: CUST2913 | C100: Meena Reddy | D100: meena27@email.com | E100: Home Office | F100: 2024-10-13 | G100: 2024-10-14 | H100: 2024-10-20 | I100: 6 | J100: East | K100: Odisha | L100: Odisha | M100: PRD4464 | N100: Microwave | O100: Home & Kitchen | P100: Appliances | Q100: Prestige | R100: 5 | S100: 10569.21 | T100: 15 | U100: 44919.14 | V100: 25101.13 | W100: 19818.01 | X100: 44.12 | Y100: 149 | Z100: EMI | AA100: Shipped | AB100: No
...

Sheet Product_Master
A1: Product_ID | B1: Product_Name | C1: Category | D1: Sub_Category | E1: Brand | F1: MRP_INR | G1: Cost_Price_INR | H1: Stock_Units | I1: Avg_Rating | J1: Total_Reviews | K1: Launch_Date | L1: Bestseller
A2: PRD1001 | B2: iPhone 15 | C2: Electronics | D2: Smartphones | E2: Apple | F2: 45664.21 | G2: 27979.28 | H2: 422 | I2: 3.6 | J2: 170 | K2: 2020-07-08 | L2: Yes
A3: PRD1002 | B3: Samsung S24 | C3: Electronics | D3: Smartphones | E3: OnePlus | F3: 21029 | G3: 11392.32 | H3: 491 | I3: 3.4 | J3: 976 | K3: 2023-01-07 | L3: No
A4: PRD1003 | B4: OnePlus 12 | C4: Electronics | D4: Smartphones | E4: MuscleBlaze | F4: 5633.99 | G4: 2646.66 | H4: 237 | I4: 5 | J4: 1725 | K4: 2023-06-08 | L4: Yes
A5: PRD1004 | B5: Realme 11 | C5: Electronics | D5: Smartphones | E5: Adidas | F5: 4608.48 | G5: 2205.84 | H5: 29 | I5: 3.7 | J5: 3681 | K5: 2022-02-18 | L5: Yes
A6: PRD1005 | B6: Xiaomi 13T | C6: Electronics | D6: Smartphones | E6: Wiley | F6: 42162.28 | G6: 19766.67 | H6: 337 | I6: 4.7 | J6: 1206 | K6: 2022-04-19 | L6: No
A7: PRD1006 | B7: Dell Inspiron | C7: Electronics | D7: Laptops | E7: Philips | F7: 41704.04 | G7: 20761.42 | H7: 317 | I7: 4.3 | J7: 4685 | K7: 2018-09-13 | L7: Yes
A8: PRD1007 | B8: HP Pavilion | C8: Electronics | D8: Laptops | E8: Samsung | F8: 13750.78 | G8: 8691.55 | H8: 143 | I8: 4.9 | J8: 1168 | K8: 2022-01-15 | L8: Yes
A9: PRD1008 | B9: Lenovo IdeaPad | C9: Electronics | D9: Laptops | E9: Samsung | F9: 6469.24 | G9: 2861.15 | H9: 21 | I9: 4.2 | J9: 2189 | K9: 2018-06-17 | L9: Yes
A10: PRD1009 | B10: Asus VivoBook | C10: Electronics | D10: Laptops | E10: HP | F10: 46462.44 | G10: 27897.76 | H10: 64 | I10: 4.6 | J10: 4913 | K10: 2020-08-16 | L10: No
A11: PRD1010 | B11: MacBook Air | C11: Electronics | D11: Laptops | E11: Nike | F11: 23718.11 | G11: 11243.58 | H11: 127 | I11: 4.4 | J11: 1725 | K11: 2023-06-11 | L11: Yes
A12: PRD1011 | B12: TWS Earbuds | C12: Electronics | D12: Accessories | E12: Wiley | F12: 10158.95 | G12: 4969.61 | H12: 92 | I12: 3.2 | J12: 1429 | K12: 2021-07-18 | L12: No
A13: PRD1012 | B13: Power Bank | C13: Electronics | D13: Accessories | E13: Amazon Basics | F13: 13767.52 | G13: 8584.41 | H13: 352 | I13: 3.6 | J13: 2733 | K13: 2020-01-26 | L13: Yes
... A71: PRD1070 | B71: Multivitamin | C71: Sports & Fitness | D71: Nutrition | E71: HP | F71: 44164.88 | G71: 18083.3 | H71: 255 | I71: 4.6 | J71: 389 | K71: 2020-12-26 | L71: No

Sheet Customer_Segments
A1: Customer_ID | B1: Customer_Name | C1: Segment | D1: State | E1: Region | F1: Total_Orders | G1: Total_Spend_INR | H1: Avg_Order_Value | I1: Last_Order_Date | J1: Days_Since_Last_Order | K1: Preferred_Category | L1: Preferred_Payment | M1: Customer_Tier | N1: Churn_Risk
A2: CUST1000 | B2: Rahul Kumar | C2: SMB | D2: Bihar | E2: East | F2: 19 | G2: 16791.5 | H2: 883.76 | I2: 2024-07-27 | J2: 158 | K2: Clothing | L2: UPI | M2: Silver | N2: Medium
A3: CUST1001 | B3: Amit Singh | C3: Corporate | D3: Goa | E3: West | F3: 21 | G3: 106805.35 | H3: 5085.97 | I3: 2024-10-27 | J3: 66 | K3: Clothing | L3: EMI | M3: Platinum | N3: Low
A4: CUST1002 | B4: Arjun Singh | C4: Corporate | D4: West Bengal | E4: East | F4: 1 | G4: 192592.59 | H4: 192592.59 | I4: 2024-10-31 | J4: 62 | K4: Books | L4: Debit Card | M4: Platinum | N4: Low
A5: CUST1003 | B5: Divya Singh | C5: Home Office | D5: Maharashtra | E5: West | F5: 27 | G5: 177088.19 | H5: 6558.82 | I5: 2024-06-21 | J5: 194 | K5: Home & Kitchen | L5: EMI | M5: Platinum | N5: High
A6: CUST1004 | B6: Rohit Nair | C6: Home Office | D6: Tamil Nadu | E6: South | F6: 7 | G6: 172078.73 | H6: 24582.68 | I6: 2024-01-05 | J6: 362 | K6: Clothing | L6: Digital Wallet | M6: Platinum | N6: High
A7: CUST1005 | B7: Manish Verma | C7: Corporate | D7: Gujarat | E7: West | F7: 19 | G7: 135455.74 | H7: 7129.25 | I7: 2024-10-23 | J7: 70 | K7: Electronics | L7: Digital Wallet | M7: Platinum | N7: Low
A8: CUST1006 | B8: Priya Nair | C8: Consumer | D8: Andhra Pradesh | E8: South | F8: 23 | G8: 115921.46 | H8: 5040.06 | I8: 2024-10-20 | J8: 73 | K8: Books | L8: EMI | M8: Platinum | N8: Low
A9: CUST1007 | B9: Rahul Mehta | C9: Corporate | D9: Bihar | E9: East | F9: 18 | G9: 147221.56 | H9: 8178.98 | I9: 2024-02-27 | J9: 309 | K9: Books | L9: Debit Card | M9: Platinum | N9: High
A10: CUST1008 | B10: Divya Reddy | C10: Home Office | D10: Rajasthan | E10: North | F10: 9 | G10: 17304.37 | H10: 1922.71 | I10: 2024-04-03 | J10: 273 | K10: Books | L10: Credit Card | M10: Silver | N10: High
A11: CUST1009 | B11: Manish Singh | C11: Home Office | D11: Gujarat | E11: West | F11: 7 | G11: 7187.22 | H11: 1026.75 | I11: 2024-04-10 | J11: 266 | K11: Sports & Fitness | L11: EMI | M11: Bronze | N11: High
A12: CUST1010 | B12: Manish Verma | C12: Consumer | D12: Rajasthan | E12: North | F12: 22 | G12: 147761.77 | H12: 6716.44 | I12: 2024-05-20 | J12: 226 | K12: Sports & Fitness | L12: Cash on Delivery | M12: Platinum | N12: High
A13: CUST1011 | B13: Manish Singh | C13: SMB | D13: Kerala | E13: South | F13: 28 | G13: 82495.61 | H13: 2946.27 | I13: 2024-12-29 | J13: 3 | K13: Electronics | L13: Debit Card | M13: Gold | N13: Low
... A1002: CUST2000 | B1002: Rekha Verma | C1002: Consumer | D1002: Karnataka | E1002: South | F1002: 27 | G1002: 180236.61 | H1002: 6675.43 | I1002: 2024-08-26 | J1002: 128 | K1002: Home & Kitchen | L1002: Debit Card | M1002: Platinum | N1002: Medium

Sheet Monthly_KPIs
A1: Year | B1: Month | C1: Category | D1: Region | E1: Total_Orders | F1: Revenue_INR | G1: COGS_INR | H1: Gross_Profit_INR | I1: Profit_Margin_Pct | J1: Avg_Order_Value | K1: Returns | L1: Return_Rate_Pct | M1: New_Customers
A2: 2022 | B2: 2022-01 | C2: Electronics | D2: North | E2: 207 | F2: 97798.16 | G2: 56935.87 | H2: 40862.29 | I2: 41.78 | J2: 472.45 | K2: 22 | L2: 10.63 | M2: 44
A3: 2022 | B3: 2022-01 | C3: Electronics | D3: South | E3: 101 | F3: 131045.36 | G3: 72854.2 | H3: 58191.16 | I3: 44.41 | J3: 1297.48 | K3: 13 | L3: 12.87 | M3: 43
A4: 2022 | B4: 2022-01 | C4: Electronics | D4: East | E4: 99 | F4: 2638714.6 | G4: 1795840.1 | H4: 842874.56 | I4: 31.94 | J4: 26653.68 | K4: 18 | L4: 18.18 | M4: 52
A5: 2022 | B5: 2022-01 | C5: Electronics | D5: West | E5: 93 | F5: 3540125 | G5: 1887164.7 | H5: 1652960.3 | I5: 46.69 | J5: 38065.86 | K5: 30 | L5: 32.26 | M5: 91
A6: 2022 | B6: 2022-01 | C6: Clothing | D6: North | E6: 115 | F6: 4759961.6 | G6: 2652446.6 | H6: 2107515 | I6: 44.28 | J6: 41390.97 | K6: 4 | L6: 3.48 | M6: 93
A7: 2022 | B7: 2022-01 | C7: Clothing | D7: South | E7: 46 | F7: 3937638.6 | G7: 2695247.4 | H7: 1242391.2 | I7: 31.55 | J7: 85600.84 | K7: 0 | L7: 0 | M7: 42
A8: 2022 | B8: 2022-01 | C8: Clothing | D8: East | E8: 98 | F8: 3333311.2 | G8: 1898593.2 | H8: 1434718.1 | I8: 43.04 | J8: 34013.38 | K8: 22 | L8: 22.45 | M8: 42
A9: 2022 | B9: 2022-01 | C9: Clothing | D9: West | E9: 139 | F9: 921735.6 | G9: 571433.58 | H9: 350302.02 | I9: 38 | J9: 6631.19 | K9: 2 | L9: 1.44 | M9: 29
A10: 2022 | B10: 2022-01 | C10: Home & Kitchen | D10: North | E10: 264 | F10: 4327755.1 | G10: 2196400 | H10: 2131355.2 | I10: 49.25 | J10: 16393.01 | K10: 15 | L10: 5.68 | M10: 22
A11: 2022 | B11: 2022-01 | C11: Home & Kitchen | D11: South | E11: 99 | F11: 1412723.1 | G11: 737233.14 | H11: 675489.94 | I11: 47.81 | J11: 14269.93 | K11: 8 | L11: 8.08 | M11: 56
A12: 2022 | B12: 2022-01 | C12: Home & Kitchen | D12: East | E12: 133 | F12: 981158.01 | G12: 684601.21 | H12: 296556.8 | I12: 30.23 | J12: 7377.13 | K12: 16 | L12: 12.03 | M12: 75
A13: 2022 | B13: 2022-01 | C13: Home & Kitchen | D13: West | E13: 164 | F13: 1637947 | G13: 1023540 | H13: 614407.06 | I13: 37.51 | J13: 9987.48 | K13: 0 | L13: 0 | M13: 46
... A721: 2024 | B721: 2024-12 | C721: Sports & Fitness | D721: West | E721: 180 | F721: 1554046 | G721: 995301.65 | H721: 558744.36 | I721: 35.95 | J721: 8633.59 | K721: 23 | L721: 12.78 | M721: 33
